{"0":{"name":"SALVATION ARMY PRIMARY SCHOOL I","abbreviation":"001"},"1":{"name":"SALVATION ARMY PRIMARY SCHOOL II","abbreviation":"002"},"2":{"name":"SALVATION ARMY PRIMARY SCHOOL III","abbreviation":"003"},"3":{"name":"SALVATION ARMY PRIMARY SCHOOL IV","abbreviation":"004"},"4":{"name":"METHODIST PRIMARY SCHOOL I","abbreviation":"005"},"5":{"name":"METHODIST PRIMARY SCHOOL II","abbreviation":"006"},"6":{"name":"METHODIST PRIMARY SCHOOL III","abbreviation":"007"},"7":{"name":"CARTER STREET PRIMARY SCHOOL I","abbreviation":"008"},"8":{"name":"CARTER STREET PRIMARY SCHOOL II","abbreviation":"009"},"9":{"name":"CARTER STREET PRIMARY SCHOOL III","abbreviation":"010"},"10":{"name":"CARTER STREET PRIMARY SCHOOL IV","abbreviation":"011"},"11":{"name":"CARTER STREET PRIMARY SCHOOL V","abbreviation":"012"},"12":{"name":"METHODIST PRIMARY SCHOOL IV","abbreviation":"013"},"13":{"name":"METHODIST PRIMARY SCHOOL V","abbreviation":"014"},"14":{"name":"MOORE HOUSE STREET PRIMARY SCHOOL","abbreviation":"015"},"15":{"name":"RECREATION CLUB-OPP. STADIUM","abbreviation":"016"},"16":{"name":"CARTER STREET HEALTH CENTRE I","abbreviation":"017"},"17":{"name":"CARTER STREET HEALTH CENTRE II","abbreviation":"018"}}