{"0":{"name":"SHIYAR KOGO \/ KOFAR MARAFA","abbreviation":"001"},"1":{"name":"SHIYAR S.  AIKI \/ KOFAR YUGUDA","abbreviation":"002"},"2":{"name":"SHIYAR ZANGO\/ YAR SANTA","abbreviation":"003"},"3":{"name":"YANKUZO I   \/   PRIMARY SCHOOL","abbreviation":"004"},"4":{"name":"TAKULAWA    \/  PRIMARY SCHOOL","abbreviation":"005"},"5":{"name":"YANKUZO II  \/  UNGUWAR JOJI","abbreviation":"006"},"6":{"name":"UNG. DODO    \/   KOFAR ISAH","abbreviation":"007"},"7":{"name":"YANKUZO III \/ TSAUNIN MAKERA","abbreviation":"008"},"8":{"name":"DUTSIN BIKA \/ KOFAR MAIGARI","abbreviation":"009"},"9":{"name":"DANKO \/ KOFAR MAI GARI","abbreviation":"010"},"10":{"name":"UNGUWAN MANDE    \/  FALANIN DODO","abbreviation":"011"},"11":{"name":"MALLAMAWA I   \/  PRIMARY SCHOOL","abbreviation":"012"},"12":{"name":"MALLAMAWA II  \/ KOFAR GADO","abbreviation":"013"},"13":{"name":"KOLI KOLI  \/  PRIMARY SCHOOL","abbreviation":"014"},"14":{"name":"UNG. ALHAZA \/ FILIN SANUSI","abbreviation":"015"},"15":{"name":"ZAMFARAWA D\/GABAS","abbreviation":"016"},"16":{"name":"YARYARA MAHAUTA","abbreviation":"017"},"17":{"name":"GOVT.SEC. SCHOOL","abbreviation":"018"},"18":{"name":"TAKULAWA KAYA","abbreviation":"019"}}