{"0":{"name":"DURUMI - DURUMI GARI","abbreviation":"001"},"1":{"name":"YARA - YARA","abbreviation":"002"},"2":{"name":"K\/FADA - FADA","abbreviation":"003"},"3":{"name":"SABON LAYI - SABON LAYI","abbreviation":"004"},"4":{"name":"GIDAN MALIKI - G.MALIKI","abbreviation":"005"},"5":{"name":"MARNA - MARNA","abbreviation":"006"},"6":{"name":"ARE PRI.SCHOOL","abbreviation":"007"},"7":{"name":"BUKASAWA BUKASAWA","abbreviation":"008"},"8":{"name":"LADANAWA PRI.SCHOOL","abbreviation":"009"},"9":{"name":"CIKA-KOSHI - CIKA KOSHI","abbreviation":"010"},"10":{"name":"AGIRA - AGIRA","abbreviation":"011"},"11":{"name":"AGIRA ZANGO - AGIRA ZANGO","abbreviation":"012"},"12":{"name":"SABON LAYI GABAS","abbreviation":"013"},"13":{"name":"KOFAR YAMMA OPEN SPACE","abbreviation":"014"},"14":{"name":"MARNA PRIMARY SCHOOL","abbreviation":"015"}}