{"0":{"name":"VILLAGE SQUARE, NUNG UKANA","abbreviation":"001"},"1":{"name":"MARKET SQUARE, NUNG UKANA","abbreviation":"002"},"2":{"name":"CONVENT SCH, ANUA EKEYA","abbreviation":"003"},"3":{"name":"MARKET SQUARE, IDIBI ENIN","abbreviation":"004"},"4":{"name":"GOVT. SCH EKPENE UKIM","abbreviation":"005"},"5":{"name":"VILLAGE SQUARE, UFOK ESUK","abbreviation":"006"},"6":{"name":"VILLAGE SQUARE, OBOT INWANG","abbreviation":"007"},"7":{"name":"METH. SCH, ESUK INWANG","abbreviation":"008"},"8":{"name":"VILLAGE SQUARE, EKPENE UKIM","abbreviation":"009"},"9":{"name":"VILLAGE HALL, ASUNG ANUA, EKEYA","abbreviation":"010"},"10":{"name":"TOWN HALL, IDIBI ENIN.","abbreviation":"011"},"11":{"name":"TOWN HALL EKPENE UKIM.","abbreviation":"012"}}