{"0":{"name":"ISHAU TOWN","abbreviation":"001"},"1":{"name":"TUNGAN AMALE  I","abbreviation":"002"},"2":{"name":"TUNGAN AMALE  II","abbreviation":"003"},"3":{"name":"DAKOLO NEW","abbreviation":"004"},"4":{"name":"GWARI YAYI","abbreviation":"005"},"5":{"name":"GOTO KURMI","abbreviation":"006"},"6":{"name":"BEJI","abbreviation":"007"},"7":{"name":"KURMIN - GIWA","abbreviation":"008"},"8":{"name":"YANKE","abbreviation":"009"},"9":{"name":"GOTO RISHI","abbreviation":"010"},"10":{"name":"GEN HOSPITAL","abbreviation":"011"},"11":{"name":"GOV'T DAY  SEC SCH ISHAU","abbreviation":"012"},"12":{"name":"ANG.UBANDOMA","abbreviation":"013"},"13":{"name":"EKWARO PRI. SCH.","abbreviation":"014"},"14":{"name":"OLD DAKALO","abbreviation":"015"}}