{"0":{"name":"QUARRY AREA I","abbreviation":"001"},"1":{"name":"QUARRY AREA II","abbreviation":"002"},"2":{"name":"AWOTEDO","abbreviation":"003"},"3":{"name":"AFRICAN PRIMARY SCHOOL","abbreviation":"004"},"4":{"name":"BANK AREA  COMMERCE AND CREDIT","abbreviation":"005"},"5":{"name":"A.D.C PRY. SCHOOL, APOMU","abbreviation":"006"},"6":{"name":"ORITA AGUNLA","abbreviation":"007"},"7":{"name":"AYODELE AREA","abbreviation":"008"},"8":{"name":"OPEN SPACE OPPOSITE ADEDAYO BAKERY OKE-OLA","abbreviation":"009"},"9":{"name":"C.A.C PRY SCHOOL,QUARY, APOMU","abbreviation":"010"},"10":{"name":"ALAPOMU HIGH SCH. AWOTEDO","abbreviation":"011"},"11":{"name":"OKE-YIDI OPEN SPACE","abbreviation":"012"},"12":{"name":"OPEN SPACE OPPOSITE MECHANIC SHOP, MOLETE","abbreviation":"013"},"13":{"name":"OPEN SPACE OPPOSITE JUMBO HOSPITAL OKE-OLA","abbreviation":"014"},"14":{"name":"OPEN SPACE OPPOSITE HASIBUINALAH OIL DEPOT","abbreviation":"015"},"15":{"name":"OPEN SPACE OPPOSITE NIYASS VENTURES OKE-OLA","abbreviation":"016"}}