{"0":{"name":"BIRJI -OPEN SPACE","abbreviation":"001"},"1":{"name":"DUGUDU -OPEN SPACE","abbreviation":"002"},"2":{"name":"GANDU, OPEN SPACE","abbreviation":"003"},"3":{"name":"GEZA, PRIMARY SCHOOL","abbreviation":"004"},"4":{"name":"KOYA ,PRI. SCHOOL","abbreviation":"005"},"5":{"name":"MAHUTA, PRI. SCHOOL","abbreviation":"006"},"6":{"name":"MARKE, PRI. SCHOOL","abbreviation":"007"},"7":{"name":"MUNGAWA, OPEN SPACE","abbreviation":"008"},"8":{"name":"RUWAN KUKA, OPEN SPACE","abbreviation":"009"},"9":{"name":"SAIDAWA , PRIMARY SCHOOL","abbreviation":"010"},"10":{"name":"TAKAI, PRIMARY SCHOOL","abbreviation":"011"},"11":{"name":"TSALLEWA, OPEN SPACE","abbreviation":"012"},"12":{"name":"ZAKIRAI, PRIMARY SCHOOL","abbreviation":"013"},"13":{"name":"BIRJI II","abbreviation":"014"},"14":{"name":"KOYA II","abbreviation":"015"},"15":{"name":"SAIDAWA II","abbreviation":"016"},"16":{"name":"SAIDAWA III","abbreviation":"017"},"17":{"name":"TAKAI II","abbreviation":"018"},"18":{"name":"ZAKIRAI II","abbreviation":"019"}}