{"0":{"name":"KOFAR FADA","abbreviation":"001"},"1":{"name":"MARORO","abbreviation":"002"},"2":{"name":"RAGADA PRIMARY SCHOOL","abbreviation":"003"},"3":{"name":"RUNTUNA","abbreviation":"004"},"4":{"name":"SARKIN DUTSE IPANDO","abbreviation":"005"},"5":{"name":"UNG. MAIDA","abbreviation":"006"},"6":{"name":"UNG. MAGAJI  I","abbreviation":"007"},"7":{"name":"UNG. MAGAJI  II","abbreviation":"008"},"8":{"name":"UNG. GALADIMA","abbreviation":"009"},"9":{"name":"UNG. UBANDAWAKI","abbreviation":"010"},"10":{"name":"UNG. WAZIRI","abbreviation":"011"},"11":{"name":"UNG. YABAWA","abbreviation":"012"},"12":{"name":"LABI PRIMARY SCHOOL","abbreviation":"013"}}