{"0":{"name":"DONKO","abbreviation":"001"},"1":{"name":"GB OTINGI","abbreviation":"002"},"2":{"name":"EMI-TASHA","abbreviation":"003"},"3":{"name":"BAFO","abbreviation":"004"},"4":{"name":"KUBO","abbreviation":"005"},"5":{"name":"EMI- NDAYISA","abbreviation":"006"},"6":{"name":"KPAYI","abbreviation":"007"},"7":{"name":"MAPA","abbreviation":"008"},"8":{"name":"KPATANTI","abbreviation":"009"},"9":{"name":"ETSU - TASHA","abbreviation":"010"},"10":{"name":"EMI - WORO TASHA","abbreviation":"011"},"11":{"name":"EMI - DZANZHI","abbreviation":"012"},"12":{"name":"GAMUNU","abbreviation":"013"},"13":{"name":"NDAFA","abbreviation":"014"},"14":{"name":"WADATA MARKET","abbreviation":"015"}}