{"0":{"name":"JUNCTION OF SULAIMON ST.\/TENIOLA ST.","abbreviation":"001"},"1":{"name":"JUNCTION OF AKEWUKEWE ST.\/EHI ST.","abbreviation":"002"},"2":{"name":"EHI ST. BY HOUSE NO. 25","abbreviation":"003"},"3":{"name":"JUNCTION OF SALAMI ST.\/ILAWOYE ST.","abbreviation":"004"},"4":{"name":"AGUNTASOLO PRIMARY SCHOOL","abbreviation":"005"},"5":{"name":"AIRWAYS ROAD BY HOUSE NO. 25","abbreviation":"006"},"6":{"name":"AIRWAYS ROAD BY HOUSE NO. 10","abbreviation":"007"},"7":{"name":"JUNCTION OF SESAN MOYEGUN ST.\/AKINWOSHO ST.","abbreviation":"008"},"8":{"name":"DURO-OYEDOYIN PRIMARY SCHOOL I","abbreviation":"009"},"9":{"name":"DURO-OYEDOYIN PRIMARY SCHOOL II","abbreviation":"010"},"10":{"name":"AKEWUKEWE ST. BY HOUSE NO. 15","abbreviation":"011"},"11":{"name":"JUNCTION OF DANISA ST.\/ALUBARIKA ST.","abbreviation":"012"},"12":{"name":"JUNCTION OF WOLE COLE ST.\/ALUBARIKA ST.","abbreviation":"013"},"13":{"name":"JUNCTION OF OLOJUBO ST.\/AKINOLA ST. I","abbreviation":"014"},"14":{"name":"JUNCTION OF OLOJUBO ST.\/AKINOLA ST. II","abbreviation":"015"},"15":{"name":"JUNCTION OF ADESINA ST.\/IREPO ST. I","abbreviation":"016"},"16":{"name":"JUNCTION OF ADESINA ST.\/IREPO ST. II","abbreviation":"017"},"17":{"name":"JUNCTION OF ADESINA ST.\/ILAMOYE ST.","abbreviation":"018"},"18":{"name":"AGUNTASOLO ST. BY HOUSE NO. 50","abbreviation":"019"},"19":{"name":"JUNCTION OF OBASOLA ST.\/KAYODE OLOWU ST.","abbreviation":"020"},"20":{"name":"ADEDOYIN ST. BY HOUSE NO. 25","abbreviation":"021"},"21":{"name":"ALHAJI OLAKUNLE ST. BY HOUSE NO. 30","abbreviation":"022"},"22":{"name":"JUNCTION OF OMILANI ST.\/AKINSANYA ST.","abbreviation":"023"},"23":{"name":"JUNCTION OF AGUNTASOLO ST.\/ILE-OGBO ST.","abbreviation":"024"},"24":{"name":"JUNCTION OF OMONUBI ST.\/AROUNMOLASHE ST.","abbreviation":"025"},"25":{"name":"JUNCTION OF GBADABO ST.\/OMILANI ST.","abbreviation":"026"},"26":{"name":"FADAHUNSI ST. BY HOUSE NO. 32","abbreviation":"027"},"27":{"name":"MARTINS ST. BY HOUSE NO. 30","abbreviation":"028"},"28":{"name":"ALHAJI THANNI ST. BY HOUSE NO. 25","abbreviation":"029"},"29":{"name":"JUNCTION OF AGUNTASOLO ST.\/DARAMOLA ST.","abbreviation":"030"},"30":{"name":"AGBOOLA ST. BY HOUSE NO. 25","abbreviation":"031"},"31":{"name":"ESHINLOKUN ST. BY HOUSE NO. 25","abbreviation":"032"},"32":{"name":"ADEWUYI ST. BY HOUSE NO. 18","abbreviation":"033"},"33":{"name":"IJESHA ROAD BY HOUSE NO. 245","abbreviation":"034"},"34":{"name":"IJESHA ROAD BY HOUSE NO. 150","abbreviation":"035"},"35":{"name":"JUNCTION OF AGBEBI ST.\/IJESHA ROAD","abbreviation":"036"},"36":{"name":"TAPA ST. BY HOUSE NO. 35 - I","abbreviation":"037"},"37":{"name":"TAPA ST. BY HOUSE NO. 35 - II","abbreviation":"038"},"38":{"name":"OLUIROLU ST.\/OKE-OLORUNTEDO ST. - I","abbreviation":"039"},"39":{"name":"OLUIROLU ST.\/OKE-OLORUNTEDO ST. - II","abbreviation":"040"},"40":{"name":"ODO-OLOWU PRIMARY SCHOOL","abbreviation":"041"},"41":{"name":"ADEBO YEJO ST. BY HOUSE NO. 7","abbreviation":"042"},"42":{"name":"SIJUADK PRIMARY SCHOOL","abbreviation":"043"},"43":{"name":"OLAKUNLE ST. BY HOUSE NO. 10","abbreviation":"044"},"44":{"name":"JUNCTION OF FEMI DARAMOLA ST.\/ODO-OLOWU ST. - I","abbreviation":"045"},"45":{"name":"JUNCTION OF FEMI DARAMOLA ST.\/ODO-OLOWU ST.- II","abbreviation":"046"},"46":{"name":"ALHAJI ADEYEMI ST. BY HOUSE 11","abbreviation":"047"},"47":{"name":"JUNCTION OF ODO-OLOWU ST.\/ABANIWONDA ST.","abbreviation":"048"},"48":{"name":"JUNCTION OF JIMOH MEJI ST.\/AGUNLEJIKA ST.","abbreviation":"049"},"49":{"name":"JUNCTION OF PROPHET ADEOYE ST.\/AGUNLEJIKA ST.","abbreviation":"050"},"50":{"name":"JUNCTION OF AJIJEDIDUN ST.\/AGUNLEJIKA ST.","abbreviation":"051"},"51":{"name":"JUNCTION OF AGUNLEJIKA ST.\/TAIWO ST.","abbreviation":"052"},"52":{"name":"JIMOH AGUNBIADE ST. BY HOUSE NO. 20","abbreviation":"053"},"53":{"name":"ABOLADE ST. BY HOUSE NO. 16","abbreviation":"054"},"54":{"name":"OYENUGA ST. BY HOUSE NO. 25","abbreviation":"055"},"55":{"name":"JUNCTION OF BABS ONI ST.\/EYIOWUAWI ST.","abbreviation":"056"},"56":{"name":"ANIMASHAUN PRIMARY SCHOOL","abbreviation":"057"},"57":{"name":"AYEGBAMI STREET BY HOUSE NO. 5","abbreviation":"058"},"58":{"name":"HOUSE NO. 82 TENIOLA STREET.","abbreviation":"059"},"59":{"name":"HOUSE NO. 2 EHI STREET.","abbreviation":"060"},"60":{"name":"JUNCTION OF REDEMPTION ST.\/ILAMOYE ST. BY HOUSE NO. 14.","abbreviation":"061"},"61":{"name":"AIRWAYS ROAD BY HOUSE NO. 37.","abbreviation":"062"},"62":{"name":"AIRWAYS ROAD BY HOUSE NO 1.","abbreviation":"063"},"63":{"name":"HOUSE NO. 17, SESAN MOYEGUN STREET.","abbreviation":"064"},"64":{"name":"DURO-OYEDOYIN PRIMARY SCHOOL.","abbreviation":"065"},"65":{"name":"ASSOCIATION AVENUE BY HOUSE 8\/10.","abbreviation":"066"},"66":{"name":"ERELU-DANISA STREET BY HOUSE NO. 20.","abbreviation":"067"},"67":{"name":"ALUBARIKA STREET BESIDE IDEAL HOTEL.","abbreviation":"068"},"68":{"name":"IN FRONT OF HOUSE NO. 12, OLOJUDO STREET.","abbreviation":"069"},"69":{"name":"HOUSE NO. 36, IREPODUN STREET.","abbreviation":"070"},"70":{"name":"ADESHINA ROAD BY HOUSE NO. 75.","abbreviation":"071"},"71":{"name":"TENIOLA STREET, BY HOUSE NO. 17.","abbreviation":"072"},"72":{"name":"INFRONT OF HOUSE NO. 67, MARTINS STREET.","abbreviation":"073"},"73":{"name":"JUNCTION OF ADESHINA ST.\/ILE-OGBO ST.","abbreviation":"074"},"74":{"name":"HOUSE NO 1, FADAHUNSI STREET.","abbreviation":"075"},"75":{"name":"AGBOOLA ST. BY HOUSE NO. 19.","abbreviation":"076"},"76":{"name":"HOUSE NO. 11. OREMEJI STREET.","abbreviation":"077"},"77":{"name":"HOUSE NO 9A, IMAM THANNI STREET.","abbreviation":"078"},"78":{"name":"HOUSE NO, 69, TAPA STREET.","abbreviation":"079"},"79":{"name":"OLUIROLU STREET BY HOUSE NO. 4.","abbreviation":"080"},"80":{"name":"ODO-OLOWU PRIMARY SCHOOL.","abbreviation":"081"},"81":{"name":"HOUSE NO. 45, ADEBOYEJO STREET.","abbreviation":"082"},"82":{"name":"ADEGBESAN STREET BY HOUSE NO. 1.","abbreviation":"083"},"83":{"name":"ADAMOLEKUN  STREET BY HOUSE NO 3.","abbreviation":"084"},"84":{"name":"OPEN SPACE IN BAALE STREET.","abbreviation":"085"},"85":{"name":"ANIMASHAUN PRIMARY SCHOOL","abbreviation":"086"}}