{"0":{"name":"UMUEKEZE","abbreviation":"001"},"1":{"name":"UMAMAA\/UMUNWAOGU","abbreviation":"002"},"2":{"name":"STATE SCHOOL I, EGBU, UMUOJI","abbreviation":"003"},"3":{"name":"UMUNWAEZE TOWN HALL","abbreviation":"004"},"4":{"name":"UMUOSHIE V.C","abbreviation":"005"},"5":{"name":"STATE SCHOOL II, EGBU","abbreviation":"006"},"6":{"name":"IHIE STATE SCHOOL I","abbreviation":"007"},"7":{"name":"IHIE STATE SCHOOL II","abbreviation":"008"},"8":{"name":"VILLAGE SQUARE\/UMUOGBU","abbreviation":"009"},"9":{"name":"UMUOSHIE WATER SIDE, EGBU","abbreviation":"010"}}