{"0":{"name":"P.H PRIMARY SCHOOL I","abbreviation":"001"},"1":{"name":"P.H PRIMARY SCHOOL II","abbreviation":"002"},"2":{"name":"P.H PRIMARY SCHOOL III","abbreviation":"003"},"3":{"name":"P.H PRIMARY SCHOOL IV","abbreviation":"004"},"4":{"name":"PABOD PRIMARY SCHOOL I","abbreviation":"005"},"5":{"name":"PABOD PRIMARY SCHOOL II","abbreviation":"006"},"6":{"name":"PABOD PRIMARY SCHOOL III","abbreviation":"007"},"7":{"name":"PABOD PRIMARY SCHOOL IV","abbreviation":"008"},"8":{"name":"PABOD PRIMARY SCHOOL V","abbreviation":"009"},"9":{"name":"PABOD PRIMARY SCHOOL VI","abbreviation":"010"},"10":{"name":"HOLY ROSARY SECONDARY SCHOOL I","abbreviation":"011"},"11":{"name":"HOLY ROSARY SECONDARY SCHOOL II","abbreviation":"012"},"12":{"name":"HOLY ROSARY SECONDARY SCHOOL III","abbreviation":"013"},"13":{"name":"HOLY ROSARY SECONDARY SCHOOL IV","abbreviation":"014"},"14":{"name":"HOLY ROSARY SECONDARY SCHOOL V","abbreviation":"015"},"15":{"name":"HOLY ROSARY SECONDARY SCHOOL VI","abbreviation":"016"},"16":{"name":"HOLY ROSARY SECONDARY SCHOOL VII","abbreviation":"017"},"17":{"name":"U.P.E SANGANA I","abbreviation":"018"},"18":{"name":"U.P.E SANGANA II","abbreviation":"019"},"19":{"name":"U.P.E SANGANA III","abbreviation":"020"},"20":{"name":"U.P.E SANGANA IV","abbreviation":"021"},"21":{"name":"U.P.E SANGANA V","abbreviation":"022"},"22":{"name":"U.P.E SANGANA VI","abbreviation":"023"},"23":{"name":"U.P.E SANGANA VII","abbreviation":"024"},"24":{"name":"U.P.E SANGANA VIII","abbreviation":"025"},"25":{"name":"U.P.E SANGANA IX","abbreviation":"026"},"26":{"name":"U.P.E SANGANA X","abbreviation":"027"},"27":{"name":"U.P.E SANGANA XI","abbreviation":"028"},"28":{"name":"U.P.E. SANGANA XII","abbreviation":"029"},"29":{"name":"U.P.E. SANGANA XIII","abbreviation":"030"},"30":{"name":"U.P.E OROGBUM SCHOOL I","abbreviation":"031"},"31":{"name":"U.P.E OROGBUM SCHOOL II","abbreviation":"032"},"32":{"name":"U.P.E OROGBUM SCHOOL III","abbreviation":"033"},"33":{"name":"U.P.E OROGBUM SCHOOL IV","abbreviation":"034"},"34":{"name":"U.P.E OROGBUM SCHOOL V","abbreviation":"035"},"35":{"name":"U.P.E OROGBUM SCHOOL VI","abbreviation":"036"},"36":{"name":"U.P.E. OROGBUM SCHOOL VII","abbreviation":"037"},"37":{"name":"P.H PRIMARY SCHOOL V","abbreviation":"038"},"38":{"name":"P.H PRIMARY SCHOOL VI","abbreviation":"039"},"39":{"name":"FAITH BAPTIST COLLEGE","abbreviation":"040"},"40":{"name":"FAITH BAPTIST COLLEGE I","abbreviation":"041"},"41":{"name":"FAITH BAPTIST COLLEGE II","abbreviation":"042"},"42":{"name":"UPE SANGANA BY BENIN STREET JUNCTION","abbreviation":"043"},"43":{"name":"UPE SANGANA BY UYO STREET JUNCTION","abbreviation":"044"},"44":{"name":"UPE SANGANA BY OPOROMA STREET JUNCTION","abbreviation":"045"},"45":{"name":"UPE SANGANA BY ABAK STREET JUNCTION","abbreviation":"046"},"46":{"name":"UPE SANGANA BY AFAM STREET JUNCTION","abbreviation":"047"},"47":{"name":"UPE OROGBUM SCHOOL VIII PRY IA","abbreviation":"048"},"48":{"name":"UPE OROGBUM SCHOOL IX PRY 1B","abbreviation":"049"},"49":{"name":"UPE OROGBUM SCHOOL X PRY 2A","abbreviation":"050"},"50":{"name":"UPE OROGBUM SCHOOL XI PRY 2B","abbreviation":"051"}}