{"0":{"name":"OPEN SQUARE OPPOSITE ST. PHILIP I","abbreviation":"001"},"1":{"name":"OPEN SQUARE OPPOSITE ST. PHILIP II","abbreviation":"002"},"2":{"name":"OPEN SQUARE OPPOSITE ST. PHILIP III","abbreviation":"003"},"3":{"name":"OPEN SQUARE OPPOSITE ST. PHILIP IV","abbreviation":"004"},"4":{"name":"OPEN SQUARE OPPOSITE ST. PHILIP V","abbreviation":"005"},"5":{"name":"OPEN SQUARE ALONG UMUDIOKA I","abbreviation":"006"},"6":{"name":"OPEN SQUARE ALONG UMUDIOKA II","abbreviation":"007"},"7":{"name":"OPEN SQUARE ALONG UMUDIOKA III","abbreviation":"008"},"8":{"name":"TRANS EKULU PRIMARY SCHOOL I","abbreviation":"009"},"9":{"name":"TRANS EKULU PRIMARY SCHOOL II","abbreviation":"010"},"10":{"name":"TRANS EKULU PRIMARY SCHOOL III","abbreviation":"011"},"11":{"name":"TRANS EKULU PRIMARY SCHOOL IV","abbreviation":"012"},"12":{"name":"TRANS EKULU PRIMARY SCHOOL V","abbreviation":"013"},"13":{"name":"UGBO ODOGWU PRIMARY SCHOOL I","abbreviation":"014"},"14":{"name":"UGBO ODOGWU PRIMARY SCHOOL II","abbreviation":"015"},"15":{"name":"UGBO ODOGWU PRIMARY SCHOOL III","abbreviation":"016"},"16":{"name":"AGU OWA I","abbreviation":"017"},"17":{"name":"AGU OWA II","abbreviation":"018"},"18":{"name":"AGU OWA III","abbreviation":"019"},"19":{"name":"AGU OWA IV","abbreviation":"020"},"20":{"name":"AGU OWA V","abbreviation":"021"},"21":{"name":"AGU ABOR HALL I","abbreviation":"022"},"22":{"name":"AGU ABOR HALL II","abbreviation":"023"},"23":{"name":"UGBO ODOGWU PRIMARY SCHOOL IV","abbreviation":"024"},"24":{"name":"UGBO ODOGWU PRIMARY SCHOOL V","abbreviation":"025"},"25":{"name":"SCHOOL OF DENTAL TECH. I","abbreviation":"026"},"26":{"name":"SCHOOL OF DENTAL TECH. II","abbreviation":"027"},"27":{"name":"TRANS EKULU PRIMARY SCHOOL VI","abbreviation":"028"},"28":{"name":"AZIGBO LANE BY PENOKS BUS STOP","abbreviation":"029"},"29":{"name":"POLE BUS STOP FEDERAL HOUSING TRANS EKULU ISUOFIA STREET","abbreviation":"030"},"30":{"name":"OBIAJA STREET, POLE BUS STOP FEDERAL HOUSING","abbreviation":"031"},"31":{"name":"IKPA OSINA JUNCTION","abbreviation":"032"},"32":{"name":"UMUDIOKA BUS STOP FEDERAL HOUSING","abbreviation":"033"},"33":{"name":"HILL VIEW TRANS - EKULU PRIMARY SCHOOL","abbreviation":"034"},"34":{"name":"MIKE TOREY AVENUE BY DAMIJA JUNCTION","abbreviation":"035"},"35":{"name":"RCC ESTATE GATE EEDC","abbreviation":"036"},"36":{"name":"OPEN SPACE ALONG MISSION ROAD BY DANDIDA GAS","abbreviation":"037"},"37":{"name":"OGBANA OKWUTE MARKET UGBO ODOUGWU","abbreviation":"038"},"38":{"name":"UGBO ODOUGWU ROAD BY MISSION ROAD","abbreviation":"039"},"39":{"name":"CBN QUARTERS BUS STOP","abbreviation":"040"},"40":{"name":"ENUGU ABOR STREET","abbreviation":"041"},"41":{"name":"OPEN SPACE ALONG OJOTO CRESCENT","abbreviation":"042"},"42":{"name":"ORIE ONUOGBA MARKET","abbreviation":"043"},"43":{"name":"HILL SIDE PRIMARY SCHOOL","abbreviation":"044"},"44":{"name":"CHIGHA STREET BY ADIMORA JUNCTION","abbreviation":"045"},"45":{"name":"UGBO OWA HEALTH CENTRE","abbreviation":"046"},"46":{"name":"UGBO ENYI PHASE SIX EXTENSION\/UGBOWA JUNCTION","abbreviation":"047"},"47":{"name":"ABAKALIKI MARKET NEW GRA","abbreviation":"048"},"48":{"name":"SANI ABACHA JUNCTION NEW GRA","abbreviation":"049"},"49":{"name":"SHEKINA GLORY JUNCTION BISHOP OTUBELU JUNIORATE","abbreviation":"050"},"50":{"name":"EKULU - GARDEN TANKER PARK","abbreviation":"051"},"51":{"name":"EZIKE JUNCTION NEW GRA","abbreviation":"052"},"52":{"name":"NIKE LAKE ROAD EZENWEREM STREET","abbreviation":"053"},"53":{"name":"OPEN UNIVERSITY NIKE LAKE ROAD NEAR TRANSFORMER","abbreviation":"054"}}