{"0":{"name":"ILE MOLASIN, LAGUN I","abbreviation":"001"},"1":{"name":"ILE MOLASIN, LAGUN II","abbreviation":"002"},"2":{"name":"ILE AGO","abbreviation":"003"},"3":{"name":"ILE TITUN ABESE","abbreviation":"004"},"4":{"name":"ISLAMIC PRIMARY SCHOOL, LAGUN","abbreviation":"005"},"5":{"name":"AKANKAN VILLAGE","abbreviation":"006"},"6":{"name":"OYEWOLA VILLAGE","abbreviation":"007"},"7":{"name":"LAMUYAN VILLAGE","abbreviation":"008"},"8":{"name":"MODUPE VILLAGE","abbreviation":"009"},"9":{"name":"RCM PRY SCH. LAGUN","abbreviation":"010"}}