{"0":{"name":"ULO IKORO UMUEZEKE HALL","abbreviation":"001"},"1":{"name":"EKE EGBU MARKET SQUARE","abbreviation":"002"},"2":{"name":"UMUDIM CIVIC HALL","abbreviation":"003"},"3":{"name":"COMMUNITY SCHOOL II, DIMNEZE","abbreviation":"004"},"4":{"name":"COMMUNITY SCHOOL I, DIMNEZE","abbreviation":"005"},"5":{"name":"UMUDURUEHIE VILLAGE HALL","abbreviation":"006"},"6":{"name":"UMUEHIENZE HALL","abbreviation":"007"},"7":{"name":"UMUDURUOMA HALL","abbreviation":"008"},"8":{"name":"UKWUACHI SQUARE","abbreviation":"009"},"9":{"name":"UMUAKUNNE IKORO HALL","abbreviation":"010"},"10":{"name":"UMUAKPA VILLAGE HALL","abbreviation":"011"}}