{"0":{"name":"BINANGO","abbreviation":"001"},"1":{"name":"IGBAK","abbreviation":"002"},"2":{"name":"BASSAN HAUSAWA","abbreviation":"003"},"3":{"name":"KIHANG","abbreviation":"004"},"4":{"name":"DUTSEN KURA","abbreviation":"005"},"5":{"name":"KATUMAI","abbreviation":"006"},"6":{"name":"PHASE  II A","abbreviation":"007"},"7":{"name":"ZAGUN HAUSAWA I","abbreviation":"008"},"8":{"name":"IDIRE KASARI","abbreviation":"009"},"9":{"name":"KURIK","abbreviation":"010"},"10":{"name":"IGBAJI","abbreviation":"011"},"11":{"name":"BINANGO","abbreviation":"012"},"12":{"name":"PHASE  II B","abbreviation":"013"},"13":{"name":"ZAGUN HAUSAWA II","abbreviation":"014"},"14":{"name":"IGBAK AKOH","abbreviation":"015"},"15":{"name":"AKASSARU","abbreviation":"016"},"16":{"name":"NYAKALA","abbreviation":"017"},"17":{"name":"COMPANY KIHANG","abbreviation":"018"},"18":{"name":"KIGOLOI","abbreviation":"019"},"19":{"name":"CIVIL DEFNCE OFFICE","abbreviation":"020"},"20":{"name":"KISSAGIP","abbreviation":"022"},"21":{"name":"KATUMAI B","abbreviation":"023"},"22":{"name":"PHASE II BLOCK D8","abbreviation":"024"},"23":{"name":"PHASE II BLOCK D85","abbreviation":"025"},"24":{"name":"KATUMAI C","abbreviation":"026"},"25":{"name":"KUBANKUSHIT","abbreviation":"027"},"26":{"name":"UHUK","abbreviation":"028"},"27":{"name":"UBANAHO","abbreviation":"029"},"28":{"name":"KUBAN BINANGO C","abbreviation":"030"},"29":{"name":"PHASE IIB I","abbreviation":"031"}}