{"0":{"name":"BAGEGA I\/KANWURI","abbreviation":"001"},"1":{"name":"BAGEGA II\/MAKARANTA","abbreviation":"002"},"2":{"name":"TUBUKI\/GARKA","abbreviation":"003"},"3":{"name":"MALLAMAWA\/PRI. SCH.","abbreviation":"004"},"4":{"name":"KAWAYE I \/MAKARANTA","abbreviation":"005"},"5":{"name":"KAWAYE  II\/KANWURI","abbreviation":"006"},"6":{"name":"DAWON -JIYA\/KANWURI","abbreviation":"007"},"7":{"name":"DUZA\/PRI. SCH","abbreviation":"008"},"8":{"name":"DANGAZAU\/PRI. SCH","abbreviation":"009"},"9":{"name":"DUTSI\/GARKA","abbreviation":"010"},"10":{"name":"ZAMFARAWA\/PRI. SCHOOL","abbreviation":"011"},"11":{"name":"KASUMKA\/PRI. SCHOOL","abbreviation":"012"},"12":{"name":"MAKAKARI\/PRI. SCHOOL","abbreviation":"013"},"13":{"name":"GARKAR AJIYA BAKIN KASUWA","abbreviation":"014"},"14":{"name":"BAGEGA ASIBITI","abbreviation":"015"},"15":{"name":"TUBUKI MAKARANTA","abbreviation":"016"},"16":{"name":"KAWAYE ASIBITI","abbreviation":"017"},"17":{"name":"SHIYAR LIMAN","abbreviation":"018"},"18":{"name":"TUNGAR DAJI P S","abbreviation":"019"},"19":{"name":"TUNTUJA PRI SCH","abbreviation":"020"},"20":{"name":"SUMKE G\/HAKIMI","abbreviation":"021"},"21":{"name":"MAKAKARI G\/HAKIMI","abbreviation":"022"}}