{"0":{"name":"ALONG AKINOLA ST. AGUDA","abbreviation":"001"},"1":{"name":"ALONG OYATOGUN ST.","abbreviation":"002"},"2":{"name":"JUNCTION OF AJAYI\/FOLAWEWO ST. I","abbreviation":"003"},"3":{"name":"JUNCTION OF AJAYI\/FOLAWEWO ST. II","abbreviation":"004"},"4":{"name":"ALONG FOLAWEWO ST.","abbreviation":"005"},"5":{"name":"JUNCTION OF ATINUKE MOBOLAJI ST.","abbreviation":"006"},"6":{"name":"ALONG ATINUKE ST.","abbreviation":"007"},"7":{"name":"ALONG SHORINMADE ST. I","abbreviation":"008"},"8":{"name":"ALONG SHORINMADE ST. II","abbreviation":"009"},"9":{"name":"JUNCTION OF FADEYI\/MUYIBI ST.","abbreviation":"010"},"10":{"name":"JUNCTION OF OREKUPOLATI\/OKUNOWO ST.","abbreviation":"011"},"11":{"name":"IN FRONT OF NO. 5 OLADOYINBO ST. I","abbreviation":"012"},"12":{"name":"IN FRONT OF NO. 5 OLADOYINBO ST. II","abbreviation":"013"},"13":{"name":"IN FRONT OF NO. 30 OLADOYINBO ST.","abbreviation":"014"},"14":{"name":"JUNCTION OF AMUDATU\/KOLA DAVID I","abbreviation":"015"},"15":{"name":"JUNCTION OF AMUDATU\/KOLA DAVID II","abbreviation":"016"},"16":{"name":"JUNCTION OF OLANIPEKUN\/OTUYELU ST.","abbreviation":"017"},"17":{"name":"ALONG FADEYI ST. I","abbreviation":"018"},"18":{"name":"ALONG FADEYI ST. II","abbreviation":"019"},"19":{"name":"ALONG OGUNSOLA ST. I","abbreviation":"020"},"20":{"name":"ALONG ADEDOYIN ST. II","abbreviation":"021"},"21":{"name":"ALONG ADEDOYIN ST.","abbreviation":"022"},"22":{"name":"JUNCTION OF TUNDE GABBY\/OSAYE I","abbreviation":"023"},"23":{"name":"JUNCTION OF TUNDE GABBY\/OSAYE II","abbreviation":"024"},"24":{"name":"ALONG OSAYE ST. I","abbreviation":"025"},"25":{"name":"ALONG OSAYE ST. II","abbreviation":"026"},"26":{"name":"JUNCTION OF SHONOLA\/ISHERI RD.","abbreviation":"027"},"27":{"name":"ALONG SHONOLA ST. I","abbreviation":"028"},"28":{"name":"ALONG SHONOLA ST. II","abbreviation":"029"},"29":{"name":"JUNCTION OF ONDO\/AJAYI RD.","abbreviation":"030"},"30":{"name":"JUNCTION OF ABOABA\/AJAYI","abbreviation":"031"},"31":{"name":"JUNCTION OF AJAYI\/ADESINA","abbreviation":"032"},"32":{"name":"ALONG ADESINA ST.","abbreviation":"033"},"33":{"name":"ALONG IREPODUN ST.","abbreviation":"034"},"34":{"name":"ALONG OSAYEMI ST.","abbreviation":"035"},"35":{"name":"IN FRONT OF NO. 100 AYO ALABI ST. I","abbreviation":"036"},"36":{"name":"IN FRONT OF NO. 100 AYO ALABI ST. II","abbreviation":"037"},"37":{"name":"ALONG IFESOWOPO ST.","abbreviation":"038"},"38":{"name":"ALONG SUNMONU ST.","abbreviation":"039"},"39":{"name":"JUNCTION OF OLOGUN\/OTUNBA ST.","abbreviation":"040"},"40":{"name":"ALONG AYANLEYE ST.","abbreviation":"041"},"41":{"name":"ALONG FADAHUNSI ST.","abbreviation":"042"},"42":{"name":"OKE IRA PRY. SCH.","abbreviation":"043"},"43":{"name":"JUNCTION OF MODINATU\/IREBAWA","abbreviation":"044"},"44":{"name":"JUNCTION OF LAWSON\/OYEDIRAN","abbreviation":"045"},"45":{"name":"ALONG AYO ALABI ST. IN FRONT OF SHOPPING CENTRE I","abbreviation":"046"},"46":{"name":"ALONG AYO ALABI ST. IN FRONT OF SHOPPING CENTRE II","abbreviation":"047"},"47":{"name":"IN FRONT OF NO. 52\/54 AYO ALABI","abbreviation":"048"},"48":{"name":"JUNCTION OF BABATUNDE\/OLANIYAN","abbreviation":"049"},"49":{"name":"JUNCTION OF MORENIKE\/ADEDIRAN ST.","abbreviation":"050"},"50":{"name":"JUNCTION OF BAYO ADEYEMO\/OGUNDELE","abbreviation":"051"},"51":{"name":"ALONG BAYO ADEYEMO ST.","abbreviation":"052"},"52":{"name":"ALONG OGUNSOLA ST.","abbreviation":"053"},"53":{"name":"AT MIDDLE OF ADESINA ST.","abbreviation":"054"},"54":{"name":"ALONG FADUNSI ST.","abbreviation":"055"},"55":{"name":"OPEN SPACE AT AYO ALABI ST.","abbreviation":"056"},"56":{"name":"JUNCTION OF ABOABA\/AJAYI","abbreviation":"057"},"57":{"name":"IN FORNT OF CHERUBIM & SERAPHIM CHURCH, CELESTIAL AVENUE POWER LINE","abbreviation":"058"},"58":{"name":"JUNCTION OF 12. AJAYI ROAD","abbreviation":"059"},"59":{"name":"JUNCTION OF TEMITOPE STR","abbreviation":"060"},"60":{"name":"JUNCTION OF RISI OJIKUTU","abbreviation":"061"},"61":{"name":"17 SHORINMADE STR","abbreviation":"062"},"62":{"name":"JUNCTION OF OREMETA STR","abbreviation":"063"},"63":{"name":"NO 8 OLADOYINBO STR","abbreviation":"064"},"64":{"name":"NO 9 OLADOYINBO STR","abbreviation":"065"},"65":{"name":"25  KOKUMO STR\/JUNCTION OF AMUDATU STR","abbreviation":"066"},"66":{"name":"IN FRONT OF YEMO SCH ADU STR","abbreviation":"067"},"67":{"name":"IN FRONT OF LADY K HOUSE KOLA DAVID STR","abbreviation":"068"},"68":{"name":"NO 3 FADEYI STR","abbreviation":"069"},"69":{"name":"BY THE MAIN GATE ADEDOYIN STR.","abbreviation":"070"},"70":{"name":"14 ADEDOYIN STREET","abbreviation":"071"},"71":{"name":"IN FRONT OF OAK SCH\/JUNCTION OF TUNDE OSAYE STR.","abbreviation":"072"},"72":{"name":"IYE \/KOKUMO JUNCTION","abbreviation":"073"},"73":{"name":"IN FRONT OF IMOASIKO HOTEL","abbreviation":"074"},"74":{"name":"IN FRONT OF HIL TOP CITY SCHOOL SHONOLA","abbreviation":"075"},"75":{"name":"SURU STREET","abbreviation":"076"},"76":{"name":"ALONG AJAYI ROAD","abbreviation":"077"},"77":{"name":"NO 39 ONDO STREET","abbreviation":"078"},"78":{"name":"NO 31 AJAYI ROAD","abbreviation":"079"},"79":{"name":"JUNCTION OF IREPODUN STR.","abbreviation":"080"},"80":{"name":"NO 21 OSAYEMI STREET","abbreviation":"081"},"81":{"name":"ALONG IREPODUN.","abbreviation":"082"},"82":{"name":"JUNCTION O F LISABI\/CHURCH STR.","abbreviation":"083"},"83":{"name":"JUNCTION OF SUNMONU STR\/ADEYEMI ALAO","abbreviation":"084"},"84":{"name":"JUNCTION OF APATA STR IN FRNT OF BAALE ABOWABA PALACE","abbreviation":"085"},"85":{"name":"FRONT OF BAALE'S PALACE ABDULLAHI","abbreviation":"086"},"86":{"name":"FRONT OF 23 LAWSON STR","abbreviation":"087"},"87":{"name":"OKE IRA PRIMARY SCHOOL","abbreviation":"088"},"88":{"name":"OKE IRA JUNIOR SECONDARY SCH","abbreviation":"089"},"89":{"name":"JUNCTION OF ILORI CLOSE APATA","abbreviation":"090"},"90":{"name":"JUNCTION OF OYEDIRAN","abbreviation":"091"},"91":{"name":"IN FRONT OF NO 3 OLA STREET","abbreviation":"092"},"92":{"name":"OKE-IRA PRY. SCHOOL APATA STR.","abbreviation":"093"},"93":{"name":"IN FRONT OF NO 67 AYO ALABI","abbreviation":"094"},"94":{"name":"NO 22 ADEBIMPE STR OFF ANIPUPO STR","abbreviation":"095"},"95":{"name":"IN FRONT OF NO10 FADUNSI AVENUE","abbreviation":"096"},"96":{"name":"JUNCTION OF OLOGUN STR. AYO ALABI","abbreviation":"097"},"97":{"name":"IN FRONT OF NO. 12 CELESTIAL AVENUE","abbreviation":"098"},"98":{"name":"18B CELESTIAL AVENUE BEHIND COUNCIL","abbreviation":"099"},"99":{"name":"IN FRONT OF NO25 CELESTIAL AVENUE","abbreviation":"100"}}