{"0":{"name":"BOME\/OPUMBU-IBAKA","abbreviation":"001"},"1":{"name":"OPUSOKO IBAKA","abbreviation":"002"},"2":{"name":"OPUKPAKI COMPOUND IBAKA","abbreviation":"003"},"3":{"name":"BORUNGOLAKA COMPOUND IBAKA","abbreviation":"004"},"4":{"name":"KALAM COMPOUND IBAKA","abbreviation":"005"},"5":{"name":"MARKET SQUARE IBAKA","abbreviation":"006"},"6":{"name":"BOME\/OPUKPAKU CPL IBAKA","abbreviation":"007"},"7":{"name":"BOME EDWIN CHUKU-AMA","abbreviation":"008"},"8":{"name":"TUBOMIEYE KIRI","abbreviation":"009"},"9":{"name":"KARAMA-KIRI","abbreviation":"010"},"10":{"name":"SUNDAY PALMER KIRI","abbreviation":"011"},"11":{"name":"ADOKIATE KIRI","abbreviation":"012"},"12":{"name":"OKIRI'S COMPOUND","abbreviation":"013"}}