{"0":{"name":"SAULAWA \/ YAN SALI","abbreviation":"001"},"1":{"name":"TASHA I \/ KAN WURI","abbreviation":"002"},"2":{"name":"FADA \/ KASUWA GARI","abbreviation":"003"},"3":{"name":"GUDASHI   \/  PRIMARY SCHOOL","abbreviation":"004"},"4":{"name":"KUMBI    \/  PRIMARY SCHOOL","abbreviation":"005"},"5":{"name":"HURDI   \/  GARKAR HAKIMI","abbreviation":"006"},"6":{"name":"ZAMFARAWA   \/  PRIMARY SCHOOL","abbreviation":"007"},"7":{"name":"MAIMARAHU   \/  PRIMARY SCHOOL","abbreviation":"008"},"8":{"name":"KASANFANI \/ PRIMARY SCHOOL","abbreviation":"009"},"9":{"name":"GIDAN MANI \/ GARKAR HAKIMI","abbreviation":"010"},"10":{"name":"WABI \/ GARKAR HAKIMI","abbreviation":"011"},"11":{"name":"KABOSO \/ PRIMARY SCHOOL","abbreviation":"012"},"12":{"name":"YALWA \/ PRIMARY SCHOOL","abbreviation":"013"},"13":{"name":"MANYAN RUWAYE \/   PRIMARY SCHOOL","abbreviation":"014"},"14":{"name":"MAKINI \/ GARKAR HAKIMI","abbreviation":"015"},"15":{"name":"GETSO  \/  PRIMARY SCHOOL","abbreviation":"016"},"16":{"name":"UNASHI  \/  PRIMARY SCHOOL","abbreviation":"017"},"17":{"name":"ZARGADO   \/ PRIMARY SCHOOL","abbreviation":"018"},"18":{"name":"KUKA BIRAI   \/   PRIMARY SCHOOL","abbreviation":"019"},"19":{"name":"DARAGA  \/ PRIMARY SCHOOL","abbreviation":"020"},"20":{"name":"DANGODABE  \/  DAN FAKO","abbreviation":"021"},"21":{"name":"FARIN RUWA  \/ ASIBITI","abbreviation":"022"},"22":{"name":"DADIN DUNIYA \/ GARKAR HAKIMI","abbreviation":"023"},"23":{"name":"YAR YAHAYA  \/   PRIMARY SCHOOL","abbreviation":"024"},"24":{"name":"UBAKA   \/  PRIMARY SCHOOL","abbreviation":"025"},"25":{"name":"KASHABUDA    \/   OFISHIN HAKIMI","abbreviation":"026"},"26":{"name":"DOGODAJI \/  PRIMARY SCHOOL","abbreviation":"027"},"27":{"name":"DANKURMI MAKARANTA   \/  PRIMARY SCHOOL","abbreviation":"028"},"28":{"name":"DAN HAYI GETSO \/ GRAKAR HAKIMI","abbreviation":"029"},"29":{"name":"TASHA II \/ BAKIN TASHA","abbreviation":"030"},"30":{"name":"FADA KASUWA GARI II","abbreviation":"031"},"31":{"name":"GETSO PRI SCH II","abbreviation":"032"}}