{"0":{"name":"POPO ILIE I","abbreviation":"001"},"1":{"name":"POPO ILIE  II","abbreviation":"002"},"2":{"name":"ST. JAMES PRY. SCHOOL","abbreviation":"003"},"3":{"name":"TEMIDIRE TOWN HALL","abbreviation":"004"},"4":{"name":"TEMIDIRE COCOA STORE","abbreviation":"005"},"5":{"name":"OLORIGA  I","abbreviation":"006"},"6":{"name":"OLORIGA  II","abbreviation":"007"},"7":{"name":"POSTAL AGENCY","abbreviation":"008"},"8":{"name":"MOTOR PARK ILIE","abbreviation":"009"},"9":{"name":"ILIE TOWN HALL","abbreviation":"010"},"10":{"name":"ABA-ESA","abbreviation":"011"}}