{"0":{"name":"HEMEN DAMSA\/NEAR HEMEN DAMSA COMPOUND","abbreviation":"001"},"1":{"name":"TAKOR I\/SCHOOL COMPOUND","abbreviation":"002"},"2":{"name":"TAKOR II\/SCHOOL COMPOUND","abbreviation":"003"},"3":{"name":"TSE AMINDE\/NEAR TSE AMINDE COMPOUND","abbreviation":"004"},"4":{"name":"AKAMBER IKYAREM\/AKAMBE IKYAREM COMPOUND","abbreviation":"005"},"5":{"name":"LGEA SCHOOL AMUZEGHER\/SCHOOL PREMISES","abbreviation":"006"},"6":{"name":"NKST SCHOOL, TSE YUWA I\/SCHOOL PREMISES","abbreviation":"007"},"7":{"name":"NKST. SCHOOL, TSE YUWA II\/SCHOOL PREMISES","abbreviation":"008"},"8":{"name":"NKST SCHOOL, ABO\/SCHOOL PREMISES","abbreviation":"009"},"9":{"name":"LGEA; AGBER\/SCHOOL PREMISES","abbreviation":"010"},"10":{"name":"TSE-SENDE\/NEAR TSE SENDE COMPOUND","abbreviation":"011"},"11":{"name":"LGEA AMUZEGHER II\/SCHOOL COMPOUND","abbreviation":"012"},"12":{"name":"OPEN SPACE NEAR ST. FRANCIS CATHOLIC CHURCH ZEVER MBAAFAN","abbreviation":"013"},"13":{"name":"OPEN SPACE NEAR ST. PETER'S CATHOLIC CHURCH AONDOAKAA","abbreviation":"014"}}