{"0":{"name":"TSE WOMBO VILLAGE - OPEN SPACE","abbreviation":"001"},"1":{"name":"LGEA SCHOOL, IGBUR I","abbreviation":"002"},"2":{"name":"LGEA SCHOOL, IGBUR II","abbreviation":"003"},"3":{"name":"ASHIBI MARKET SQUARE","abbreviation":"004"},"4":{"name":"NKST PRI. SCHOOL, AGBONOR","abbreviation":"005"},"5":{"name":"NEAR TSE ALI HIM COMP.-MBATEVA","abbreviation":"006"},"6":{"name":"LGEA SCHOOL, TOUGH","abbreviation":"007"},"7":{"name":"ZUA MARKET SQUARE","abbreviation":"008"},"8":{"name":"LGEA SCHOOL, BUA","abbreviation":"009"},"9":{"name":"LGEA SCHOOL, AKUME","abbreviation":"010"},"10":{"name":"NEAR ZUZU ICHEGH COMP.-MBAASENEKU","abbreviation":"011"},"11":{"name":"DIWA MARKET SQUARE","abbreviation":"012"},"12":{"name":"LEPROSY CLINIC, APAA","abbreviation":"013"},"13":{"name":"OPEN SPACE AT ABANYI KOR JUNCTION","abbreviation":"014"},"14":{"name":"ABIN MKT SQR","abbreviation":"015"},"15":{"name":"GBOUGH MKT SQR, MBATEVA","abbreviation":"016"},"16":{"name":"YEGHER MKT SQR","abbreviation":"017"},"17":{"name":"MT CARMEL NUR PRI SCH, IORTYER","abbreviation":"018"},"18":{"name":"IORNONGO MKT SQR","abbreviation":"019"},"19":{"name":"FADA MKT SQR, MBATSER","abbreviation":"020"},"20":{"name":"TYOGBENDA ZEREMO, MBAMANGE","abbreviation":"021"},"21":{"name":"IYOL CHRISTU NUR PRI SCH, IORGBA","abbreviation":"022"},"22":{"name":"ADAAKU MKT SQR, ASANGE","abbreviation":"023"}}