{"0":{"name":"FADAN WATE","abbreviation":"001"},"1":{"name":"MAITOZO","abbreviation":"002"},"2":{"name":"KWASSU","abbreviation":"003"},"3":{"name":"KWASU TITI","abbreviation":"004"},"4":{"name":"NINCHE","abbreviation":"005"},"5":{"name":"UNG KAURA I","abbreviation":"006"},"6":{"name":"SAMBE","abbreviation":"007"},"7":{"name":"DOROWA","abbreviation":"008"},"8":{"name":"KWASSU II","abbreviation":"009"},"9":{"name":"UNG KAURA II","abbreviation":"010"},"10":{"name":"MODEL PRI SCH","abbreviation":"011"},"11":{"name":"LEA PRI SCH MAITOZO II","abbreviation":"012"},"12":{"name":"LEA PRI SCH MAITOZO III","abbreviation":"013"},"13":{"name":"LEA PRI SCH","abbreviation":"014"},"14":{"name":"LEA PRI SCH","abbreviation":"015"}}