{"0":{"name":"OBUKWU SQUARE I","abbreviation":"001"},"1":{"name":"OBUKWU SQUARE II","abbreviation":"002"},"2":{"name":"ATAVA SQUARE I","abbreviation":"003"},"3":{"name":"ATAVA SQUARE II","abbreviation":"004"},"4":{"name":"AKPA HALL I","abbreviation":"005"},"5":{"name":"AKPA HALL II","abbreviation":"006"},"6":{"name":"UMURIANA HALL I","abbreviation":"007"},"7":{"name":"UMURIANA HALL II","abbreviation":"008"},"8":{"name":"UMUERECHI HALL I (UMUERECHI VILLAGE SQUARE I)","abbreviation":"009"},"9":{"name":"UMUERECHI HALL II (UMUERECHI VILLAGE SQUARE II)","abbreviation":"010"},"10":{"name":"AKPI HALL","abbreviation":"011"},"11":{"name":"UMUOKA HALL","abbreviation":"012"},"12":{"name":"UMUOTOBO HALL I","abbreviation":"013"},"13":{"name":"UMUOTOBO HALL II","abbreviation":"014"},"14":{"name":"UMUOTOBO HALL III","abbreviation":"015"},"15":{"name":"UMUOTOBO HALL IV","abbreviation":"016"},"16":{"name":"C.P.S. ANAKU I","abbreviation":"017"},"17":{"name":"C.PS. ANAKU II","abbreviation":"018"},"18":{"name":"C.P.S ANAKU III","abbreviation":"019"},"19":{"name":"C.P.S ANAKU IV","abbreviation":"020"},"20":{"name":"ISIOKWE SQUARE I","abbreviation":"021"},"21":{"name":"ISIOKWE SQUARE II","abbreviation":"022"},"22":{"name":"UMUARECHI HALL II","abbreviation":"023"},"23":{"name":"AUSTIN FARMS","abbreviation":"024"},"24":{"name":"EKE CENTRAL PRIMARY SCHOOL ANAKU","abbreviation":"025"},"25":{"name":"HEALTH CENTRE IKENGA","abbreviation":"026"}}