{"0":{"name":"A.U.D. IJALE PAPA  I","abbreviation":"001"},"1":{"name":"A.U.D. IJALE PAPA  II","abbreviation":"002"},"2":{"name":"ANLG PRY SCH, IJOLE ORILE","abbreviation":"003"},"3":{"name":"SERIKI VILLAGE","abbreviation":"004"},"4":{"name":"BAPTIST PRY. SCHOOL TIBO  I","abbreviation":"005"},"5":{"name":"BAPTIST PRY. SCHOOL TIBO  II","abbreviation":"006"},"6":{"name":"MATERNITY CENTRE, OLORUNDA","abbreviation":"007"},"7":{"name":"BAPTIST SCHOOL OLORUNDA  II","abbreviation":"008"},"8":{"name":"A.L.G. BEGBINLAWO  I","abbreviation":"009"},"9":{"name":"A.L.G. BEGBINLAWO  II","abbreviation":"010"},"10":{"name":"ILOGUN ORILE VILLAGE","abbreviation":"011"},"11":{"name":"A.N.G. IDI-ORI","abbreviation":"012"},"12":{"name":"R.C.M. KEESAN ORILE  I","abbreviation":"013"},"13":{"name":"R.C.M. KEESAN ORILE  II","abbreviation":"014"},"14":{"name":"A.N.G. AKILIYI","abbreviation":"015"},"15":{"name":"AKIEGUN JUNCTION","abbreviation":"016"},"16":{"name":"A.L.G. SCHOOL FAPOTE","abbreviation":"017"}}