{"0":{"name":"PRIM. SCHOOL, MANGUNA","abbreviation":"001"},"1":{"name":"TADDAI","abbreviation":"002"},"2":{"name":"PRIM. SCHOOL, HURTI","abbreviation":"003"},"3":{"name":"PRIM. SCHOOL, KARFA","abbreviation":"004"},"4":{"name":"DISHAU","abbreviation":"005"},"5":{"name":"PRY SCH GWANDE  I","abbreviation":"006"},"6":{"name":"PRY SCH GWANDE  II","abbreviation":"007"},"7":{"name":"MAHURUMBADE","abbreviation":"008"},"8":{"name":"MAHURUM","abbreviation":"009"},"9":{"name":"TAGGAI","abbreviation":"010"},"10":{"name":"PRIM. SCHOOL, HURTI","abbreviation":"011"},"11":{"name":"TISIU","abbreviation":"012"},"12":{"name":"PRI. SCH. AYI","abbreviation":"013"},"13":{"name":"PRI. SCH. DANBWASH","abbreviation":"014"},"14":{"name":"FAKUF FOOTBALL FIELD","abbreviation":"015"},"15":{"name":"NOMADIC PRI. SCH DOI","abbreviation":"016"},"16":{"name":"NOMADIC PRI. SCH. TADDAI","abbreviation":"017"},"17":{"name":"PRI.SCH.LAKKA","abbreviation":"018"}}