{"0":{"name":"DOGARAWA I\/ CHIKIN GARI","abbreviation":"001"},"1":{"name":"UNG FULANI\/ L.E.A. ANG FULANI","abbreviation":"002"},"2":{"name":"UNG ALH BARAU\/ K\/G ALH BARAU DIKKO","abbreviation":"003"},"3":{"name":"KABAMA RANJI\/ K\/G CHINDO","abbreviation":"004"},"4":{"name":"DOGARAWA\/ K\/G MAI ANGUWAN","abbreviation":"005"},"5":{"name":"UNG NOMI\/ NOMI HOUSE","abbreviation":"006"},"6":{"name":"KWANTA RESHE\/ K\/G MAI ANGUWAN","abbreviation":"007"},"7":{"name":"UNG SAKADADI\/ UPE SAKADADI","abbreviation":"008"},"8":{"name":"UNG SARKI\/ UPE SAKADADI","abbreviation":"009"},"9":{"name":"UNG MAL ISA\/ K\/G MAL ISA","abbreviation":"010"},"10":{"name":"DAN MAI KWARUWA\/ MAISHELLARO HOUSE","abbreviation":"011"},"11":{"name":"UNG BARASHI\/ UNG BARASHI","abbreviation":"012"},"12":{"name":"UNG SARKI\/ K\/G SARKI","abbreviation":"013"},"13":{"name":"GWANDA\/ GINDIN RIMI KAROFI","abbreviation":"014"},"14":{"name":"BAUDA\/ K\/G MAI ANGUWAN","abbreviation":"015"},"15":{"name":"ZANGON DAN BARNO\/ UPE ZANGON DAN BARNO","abbreviation":"016"},"16":{"name":"GABASHIN GWANDA\/ GWANDA","abbreviation":"017"},"17":{"name":"GWANDA VILLAGE\/ K\/G MAI ANGUWAN","abbreviation":"018"},"18":{"name":"GWANDA\/ UNG MADAKI","abbreviation":"019"},"19":{"name":"DOGARAWA II\/ TANKO HOUSE","abbreviation":"020"},"20":{"name":"DANDALI CHIKIN ANGUWA DOGARAWA","abbreviation":"021"},"21":{"name":"LEA ANG FULANI II","abbreviation":"022"},"22":{"name":"MAI GWANJO ALH AHMADU HOUSE","abbreviation":"023"},"23":{"name":"LAYIN NADABO\/ALH UMARU KONGO HOUSE","abbreviation":"024"},"24":{"name":"DOGARAWA\/KONTARESHA JUNCITON UMMULKHAIR ACADEMY","abbreviation":"025"},"25":{"name":"LAYIN MASU ADUDU BY MASU ADUDU HOUSE","abbreviation":"026"},"26":{"name":"LAYIN GAMBO YAN TINKA BY GAMBO YAN TINKA HOUSE","abbreviation":"027"}}