{"0":{"name":"BAGADDI MUDI\/ KGM BAGADDI","abbreviation":"001"},"1":{"name":"LIKORO TASHA\/ KGM L\/TASHA","abbreviation":"002"},"2":{"name":"KADA - KADA I\/ PRI. SCH. K\/KADA","abbreviation":"003"},"3":{"name":"UNG. NOMAU\/ KGM NOMAU","abbreviation":"004"},"4":{"name":"KADA KADA II\/ KGM KADA KADA","abbreviation":"005"},"5":{"name":"MAHUTA GARI I\/ PRI. SCH. MAHUTA","abbreviation":"006"},"6":{"name":"UNG. SARKI\/ PRI. SCH. T\/SANI","abbreviation":"007"},"7":{"name":"UNG. GALADIMA\/ KGM GALADIMA","abbreviation":"008"},"8":{"name":"DANTARO\/ KGM DANTORO","abbreviation":"009"},"9":{"name":"UNG. GARBA\/ KGM GARBA","abbreviation":"010"},"10":{"name":"UNG. MAKERA\/ KGM MAKERA","abbreviation":"011"},"11":{"name":"UNG. GUDUGU\/ KGM GUDUGU","abbreviation":"012"},"12":{"name":"UNG. MASASSAKA\/ KGM MASASSAKA","abbreviation":"013"},"13":{"name":"UNG. DANKALA\/ KGM DANKALA","abbreviation":"014"},"14":{"name":"MAHUTA GARI II\/ PRI. SCH. MAHUTA","abbreviation":"015"},"15":{"name":"UNG. SHARU\/ KGM SHARU","abbreviation":"016"},"16":{"name":"UNG. SARKI II\/ L.E.A. PRI. SCH.","abbreviation":"017"},"17":{"name":"UNG. HAKIMI","abbreviation":"018"}}