{"0":{"name":"UNG. YARIMA, KOFAR SARKI","abbreviation":"001"},"1":{"name":"UNG. MADAKI, PRI. SCHOOL","abbreviation":"002"},"2":{"name":"UNG. MADAKI, KOFAR MADAKI","abbreviation":"003"},"3":{"name":"BARWO S\/ GARI, KOFAR SARKI","abbreviation":"004"},"4":{"name":"BARWO S\/ GARI, KOFAR MAJIDADI","abbreviation":"005"},"5":{"name":"KANJI, KOFAR GALADIMA","abbreviation":"006"},"6":{"name":"WAKKALTU, KOFAR SARKI","abbreviation":"007"},"7":{"name":"KUKAWARI, KOFAR SARKI","abbreviation":"008"},"8":{"name":"FESHINGO, KOFAR SARKI","abbreviation":"009"},"9":{"name":"LAFIYAWO,  KOFAR JAURO SHEHU","abbreviation":"010"},"10":{"name":"ZADAWA,  KOFAR JAURO AHMADU","abbreviation":"011"},"11":{"name":"DADINKOWA,  KOFAR JAURO JEIYO","abbreviation":"012"},"12":{"name":"LUMPUTI,  KOFAR JAURO MAMUDA","abbreviation":"013"}}