{"0":{"name":"LGEA SCHOOL, KABAWA","abbreviation":"001"},"1":{"name":"OPEN SPACE, VET. CLINIC, YORUBAWA AREA","abbreviation":"002"},"2":{"name":"OPEN SPACE, COOP. PREMISES","abbreviation":"003"},"3":{"name":"OPEN SPACE, EGAH","abbreviation":"004"},"4":{"name":"OPEN SPACE, ANGWA HAUSAWA  I","abbreviation":"005"},"5":{"name":"OPEN SPACE, ANGWA HAUSAWA  II","abbreviation":"006"},"6":{"name":"OPEN SPACE, GARAGE PREMISES","abbreviation":"007"},"7":{"name":"OPEN SPACE, UBIGA OHIOMOGBO  I","abbreviation":"008"},"8":{"name":"OPEN SPACE, UBIGA OHIOMOGBO  II","abbreviation":"009"},"9":{"name":"OPEN SPACE, TOWN PARK","abbreviation":"010"},"10":{"name":"OPEN SPACE, CHILD WELFARE CLINIC","abbreviation":"011"},"11":{"name":"OPEN SPACE KANO ROAD","abbreviation":"012"},"12":{"name":"OPEN SPACE OFUROBA ROAD","abbreviation":"013"},"13":{"name":"OPEN SPACE, UBIGA AGOJEJU","abbreviation":"014"}}