{"0":{"name":"KIDANDAM I-V\/ VIEWING CENTRE, KIDANDAM","abbreviation":"001"},"1":{"name":"UNG. NAKAKA I, II, U\/MALAM NAKOWA S\/LAYI\/ KOFAR MAIUNGUWA","abbreviation":"002"},"2":{"name":"UNG. DAN ZANGO I, II & U\/GOGI I, II, III\/ KOFAR MAIUNGUWA","abbreviation":"003"},"3":{"name":"TUMBURKU I, II\/ KOFAR MAIUNGUWA TUMBURKU","abbreviation":"004"},"4":{"name":"BASURFE M. RIKWA\/ KOFAR MAIUNGUWA BASURFE","abbreviation":"005"},"5":{"name":"GIDAN DUTSE I, II\/ KOFAR MAIUNGUWA G\/DUTSE","abbreviation":"006"},"6":{"name":"UNG. ROGO\/ KOFAR GIDAN MAIUNGUWA","abbreviation":"007"},"7":{"name":"SABON SARA BARDEN BAKA\/ KOFAR MAIUNGUWA S\/SARA","abbreviation":"008"},"8":{"name":"MAIDAURO I, II\/ KOFAR MAIUNGUWA","abbreviation":"009"},"9":{"name":"TOROKO\/ KOFAR MAIUNGUWA","abbreviation":"010"},"10":{"name":"KUMFA I, II\/ KOFAR MAINGUWA","abbreviation":"011"},"11":{"name":"IYATAWA I, II & ANG. S\/PADA\/ L.E.A. IYATAWA","abbreviation":"012"},"12":{"name":"IYATAWA I, II & ANG. S\/PADA\/ KOFAR MAI UNGUWA TANIMU","abbreviation":"013"},"13":{"name":"HAYIN MALLAM\/ KOFAR MAIUNGUWA","abbreviation":"014"},"14":{"name":"BARNAWA\/ RINGIM\/ BARNAWA KOFAR MAIUNGUWA","abbreviation":"015"},"15":{"name":"HAYIN FULANI\/ VIEWING CENTRE KIDANDAN","abbreviation":"016"},"16":{"name":"LGEA PRIMARY SCHOOL KIDANDAN","abbreviation":"017"},"17":{"name":"PHC KIDANDAN","abbreviation":"018"},"18":{"name":"LEA PRIMARY SCHOOL SABAON LAYI","abbreviation":"019"},"19":{"name":"UBE PRIMARY SCHOOL GOGE","abbreviation":"020"},"20":{"name":"LGEA PRIMARY SCHOOL KURBAWA","abbreviation":"021"},"21":{"name":"LGEA PRIMARY SCHOOL MAIDARO","abbreviation":"022"},"22":{"name":"LGEA PRIMARY SCHOOL IYATAWA","abbreviation":"023"},"23":{"name":"LGEA PRIMARY SCHOOL RINGIM","abbreviation":"024"},"24":{"name":"TSOHUWAN KASUWA KIDANDAN","abbreviation":"025"}}