{"0":{"name":"OBIOGWA - ISUMPE     ISUMPE  QUARTERS  I","abbreviation":"001"},"1":{"name":"OBIOGWA - ISUMPE     ISUMPE  QUARTERS  II","abbreviation":"002"},"2":{"name":"OBIOGWA - ISUMPE     ISUMPE  QUARTERS  III","abbreviation":"003"},"3":{"name":"OBIOGWA - UMUSETI    UMUSETI  QUARTERS I","abbreviation":"004"},"4":{"name":"OBIOGWA - UMUSETI    UMUSETI  QUARTERS II","abbreviation":"005"},"5":{"name":"OBIOGWA - UMUSETI    UMUSETI  QUARTERS III","abbreviation":"006"},"6":{"name":"OBIOGWA  UMUSAM     UMUSAM\/OGBEOMI","abbreviation":"007"},"7":{"name":"OBIOGWA UMUSADEGE     UMUSADEGE","abbreviation":"008"},"8":{"name":"NDUEZE PRIMARY SCHOOL -   UMUSADEGE","abbreviation":"009"},"9":{"name":"OBIOGWA   UMUSADELI","abbreviation":"010"},"10":{"name":"UKABI PRIMARY SCHOOL,    UKABI\/ABAM","abbreviation":"011"},"11":{"name":"OBIOGWA - UMUSETI     AKAKPANI  UMUSETI","abbreviation":"012"},"12":{"name":"OBIOGWA   IKILIBI  UNO","abbreviation":"013"},"13":{"name":"EBOLOGU  PRIMARY SCHOOL,  OGBE-EKE    UMUSAMUNO","abbreviation":"014"},"14":{"name":"NDUEZE  PRIMARY SCHOOL,  UMUSADEGE","abbreviation":"015"},"15":{"name":"OBIOGWA - ISUMPE      ISUMPE  QUARTERS","abbreviation":"016"}}