{"0":{"name":"OGBEABO SQUARE I","abbreviation":"001"},"1":{"name":"OGBEABO SQUARE II","abbreviation":"002"},"2":{"name":"OGBEABO SQUARE III","abbreviation":"003"},"3":{"name":"IMEOBI OGBEABO SQUARE","abbreviation":"004"},"4":{"name":"METROPOLITAN SEC. SCHOOL","abbreviation":"005"},"5":{"name":"UMUIKEM SQUARE I","abbreviation":"006"},"6":{"name":"OJIDOKO SQUARE","abbreviation":"007"},"7":{"name":"PEP SQUARE\/OKOSI ROAD","abbreviation":"008"},"8":{"name":"ILO OBIOKPORO SQUARE","abbreviation":"009"},"9":{"name":"UMUIKEM SQUARE II","abbreviation":"010"},"10":{"name":"ABUTU SQUARE","abbreviation":"011"},"11":{"name":"OPEN SPACE BESIDE NO. 5 OKOSI RD\/ST. STEPHEN RD","abbreviation":"012"},"12":{"name":"OPEN SPACE BEIDE NO. II MGBEDEME VILLAGE SQUARE\/ BISHOP ONYEABO STR.","abbreviation":"013"},"13":{"name":"OPEN SPACE BESIDE BISHOP ONYEABO OPPOSITE EZICHIMMA PRIMARY SCHOOL","abbreviation":"014"},"14":{"name":"METROPOLITAN SEC. SCHOOL II (GLO BLOCK)","abbreviation":"015"},"15":{"name":"OPEN SPACE BESIDE NO. 1 CHUKWUMA LANE","abbreviation":"016"},"16":{"name":"OPEN SPACE BESIDE NO. 3 IBEGBU STREET, OPPOSITE ILO UTO, UMUASE","abbreviation":"017"},"17":{"name":"OPEN SPACE BESIDE NO. 61 TASIA RD\/OJIBA LANE","abbreviation":"018"},"18":{"name":"OPEN SPACE BESIDE OGBENDIDA VILLAGE SQUARE, UKWU MGWULUNGWU","abbreviation":"019"},"19":{"name":"OPEN SPACE BESIDE NO. 9 OJIBA\/ABUTU LANE","abbreviation":"020"}}