{"0":{"id":"17044","name":"LIMAWA 'A'","abbreviation":"01","local_government_id":"542"},"1":{"id":"17045","name":"LIMAWA 'B'","abbreviation":"02","local_government_id":"542"},"2":{"id":"17046","name":"MAKERA","abbreviation":"03","local_government_id":"542"},"3":{"id":"17047","name":"MINNA CENTRAL","abbreviation":"04","local_government_id":"542"},"4":{"id":"17048","name":"MINNA SOUTH","abbreviation":"05","local_government_id":"542"},"5":{"id":"17049","name":"NASSARAWA 'A'","abbreviation":"06","local_government_id":"542"},"6":{"id":"17050","name":"NASSARAWA 'B'","abbreviation":"07","local_government_id":"542"},"7":{"id":"17051","name":"NASSARAWA 'C'","abbreviation":"08","local_government_id":"542"},"8":{"id":"17052","name":"SABON GARI","abbreviation":"09","local_government_id":"542"},"9":{"id":"17053","name":"TUDUN WADA NORTH","abbreviation":"10","local_government_id":"542"},"10":{"id":"17054","name":"TUDUN WADA SOUTH","abbreviation":"11","local_government_id":"542"}}