{"0":{"name":"SWASUN GABI","abbreviation":"001"},"1":{"name":"NUWAKOTA","abbreviation":"002"},"2":{"name":"EJIKO","abbreviation":"003"},"3":{"name":"LEGBOZUKUN","abbreviation":"004"},"4":{"name":"TOROKO","abbreviation":"005"},"5":{"name":"SOMMAJIGI","abbreviation":"006"},"6":{"name":"LAGA","abbreviation":"007"},"7":{"name":"BINI","abbreviation":"008"},"8":{"name":"MALAGI","abbreviation":"009"},"9":{"name":"EDOTSU","abbreviation":"010"},"10":{"name":"UKUNKUGI","abbreviation":"011"},"11":{"name":"YIKANGI - CIKAN","abbreviation":"012"},"12":{"name":"LEGBO ZUKUN - MAGI WAYA","abbreviation":"013"},"13":{"name":"BIDAFU JABA","abbreviation":"014"},"14":{"name":"KPAKOGI","abbreviation":"015"},"15":{"name":"SOMANJIGI TAKO","abbreviation":"016"},"16":{"name":"WASAGI PRY. SCHOOL","abbreviation":"017"},"17":{"name":"UBE PRY SCH EVUNTAGI CHIKEN","abbreviation":"018"}}