{"0":{"name":"BUDA HURUMI I","abbreviation":"001"},"1":{"name":"BUDA HURUMI II","abbreviation":"002"},"2":{"name":"DAWAKI BUDA","abbreviation":"003"},"3":{"name":"FAFURAI","abbreviation":"004"},"4":{"name":"GALADANCI","abbreviation":"005"},"5":{"name":"KURAYE","abbreviation":"006"},"6":{"name":"KURUNDAWA","abbreviation":"007"},"7":{"name":"KWAS HURUMI I","abbreviation":"008"},"8":{"name":"KWAS HURUMI II","abbreviation":"009"},"9":{"name":"MAKAMAN KUDU I","abbreviation":"010"},"10":{"name":"NARYA I","abbreviation":"011"},"11":{"name":"NARYA II","abbreviation":"012"},"12":{"name":"BUDA HURUMI II","abbreviation":"013"}}